bassextile_pkg/__init__.py
bassextile_pkg-1.0.0.dist-info/LICENSE
bassextile_pkg-1.0.0.dist-info/METADATA
bassextile_pkg-1.0.0.dist-info/WHEEL
bassextile_pkg-1.0.0.dist-info/top_level.txt
bassextile_pkg-1.0.0.dist-info/RECORD
