Metadata-Version: 2.1
Name: bassextile-pkg
Version: 1.0.0
Summary: Un package de calcul et de vérification
Home-page: https://github.com/pypa/sampleproject
Author: Amos Alassane
Author-email: pro4alou@gmail.com
License: UNKNOWN
Platform: UNKNOWN
Classifier: Programming Language :: Python :: 3
Classifier: License :: OSI Approved :: MIT License
Classifier: Operating System :: OS Independent
Requires-Python: >=3.6
